descmap/__init__.py
descmap/analysis/__init__.py
descmap/analysis/chemkin.py
descmap/analysis/openmkm.py
descmap/analysis/plot.py
descmap/errors.py
descmap/io.py
descmap/job.py
descmap/sampling.py
descmap/selection.py
descmap/setup.py
descmap-1.0.1.dist-info/LICENSE.md
descmap-1.0.1.dist-info/METADATA
descmap-1.0.1.dist-info/WHEEL
descmap-1.0.1.dist-info/RECORD
