Metadata-Version: 2.1
Name: descmap
Version: 1.0.1
Summary: Automatic feature selection and volcano curve generation.
License: MIT
Author: Xue Zong
Requires-Python: >=3.9,<3.12
Classifier: License :: OSI Approved :: MIT License
Classifier: Programming Language :: Python :: 3
Classifier: Programming Language :: Python :: 3.9
Classifier: Programming Language :: Python :: 3.10
Classifier: Programming Language :: Python :: 3.11
Requires-Dist: chart-studio (>=1.1.0)
Requires-Dist: matplotlib (>=3.6.3)
Requires-Dist: numpy (>=1.24.2)
Requires-Dist: pandas (>=1.5.3)
Requires-Dist: pgradd (>=2.9.5)
Requires-Dist: plotly (>=5.13.0)
Requires-Dist: pmutt (>=1.3.2)
Requires-Dist: pydoe (>=0.3.8)
Requires-Dist: rdkit (>=2022.9.4)
Requires-Dist: scikit-learn (>=1.2.1)
Requires-Dist: scipy (>=1.10.0)
Requires-Dist: vunits (>=0.0.4)
Requires-Dist: xlsxwriter (>=3.0.8)
